README.rst
setup.py
bin/raster2xyz
raster2xyz/__init__.py
raster2xyz/cli.py
raster2xyz/raster2xyz.py
raster2xyz.egg-info/PKG-INFO
raster2xyz.egg-info/SOURCES.txt
raster2xyz.egg-info/dependency_links.txt
raster2xyz.egg-info/requires.txt
raster2xyz.egg-info/top_level.txt