Metadata-Version: 1.1
Name: raster2xyz
Version: 0.1.1
Summary: Alternative and faster (vectorized) version of gdal2xyz.py
Home-page: http://github.com/cayetanobv/raster2xyz
Author: Cayetano Benavent
Author-email: cayetano.benavent@geographica.gs
License: GPLv2
Keywords: raster GIS xyz gdal
Platform: UNKNOWN
Classifier: Development Status :: 4 - Beta
Classifier: Intended Audience :: Developers
Classifier: License :: OSI Approved :: GNU General Public License v2 (GPLv2)
Classifier: Programming Language :: Python :: 2.7
Classifier: Programming Language :: Python :: 3.4
Classifier: Programming Language :: Python :: 3.5
Classifier: Operating System :: OS Independent
Classifier: Topic :: Scientific/Engineering :: GIS
